LICENSE
README.md
setup.py
ctxpro/__init__.py
ctxpro/__main__.py
ctxpro/checkers.py
ctxpro/evalsets.py
ctxpro/extract.py
ctxpro/identify.py
ctxpro/score.py
ctxpro.egg-info/PKG-INFO
ctxpro.egg-info/SOURCES.txt
ctxpro.egg-info/dependency_links.txt
ctxpro.egg-info/entry_points.txt
ctxpro.egg-info/requires.txt
ctxpro.egg-info/top_level.txt
ctxpro/rules/__init__.py
ctxpro/rules/de.py
ctxpro/rules/es.py
ctxpro/rules/fr.py
ctxpro/rules/it.py
ctxpro/rules/pl.py
ctxpro/rules/pt.py
ctxpro/rules/ru.py